{"name":"WooCommerce Products","desc":"Generate code to list products on WooCommerce","service":true,"page":true,"author":"Ihsana Team","email":"imabuilder@ihsana.com","company":"Ihsana IT Solution","form":[{"name":"wordpress-url","title":"WordPress URL","placeholder":"https:\/\/yourwordpress.com\/","help":"Your wordpress site address","attributes":"required","option":"","type":"url"},{"name":"consumer-key","title":"Consumer Key","placeholder":"ck_d89859096d0cbec7dca675ca61e78dee675c0e32","help":"","attributes":"required","option":"","type":"text"},{"name":"consumer-secret","title":"Consumer Secret","placeholder":"cs_b3e7c815725fb9d5dc899b524053d1bf23aaa060","help":"","attributes":"required","option":"","type":"text"}],"component":false,"global":false}